development/__init__.py
development/benedikt.py
development/start_telegram_cli.py
development/tests/__init__.py
development/tests/working/__init__.py
development/tests/working/aux.py
development/tests/working/run.py
docs/__init__.py
docs/conf.py
docs/figures/__init__.py
docs/figures/create.py
docs/figures/scripts/__init__.py
docs/figures/scripts/fig-distribution-joint.py
docs/figures/scripts/fig-eh-marginal-effect.py
docs/figures/scripts/fig-local-average-treatment.py
docs/figures/scripts/fig-treatment-effects.py
docs/figures/scripts/fig-weights-marginal-effect.py
docs/figures/scripts/fig_config.py
grmpy/__init__.py
grmpy/__version__.py
grmpy/grmpy_config.py
grmpy/KernReg/__init__.py
grmpy/KernReg/locpoly.py
grmpy/KernReg/locpoly_auxiliary.py
grmpy/KernReg/locpoly_linbin.py
grmpy/check/__init__.py
grmpy/check/auxiliary.py
grmpy/check/check.py
grmpy/check/custom_exceptions.py
grmpy/estimate/__init__.py
grmpy/estimate/estimate.py
grmpy/estimate/estimate_auxiliary.py
grmpy/estimate/estimate_output.py
grmpy/estimate/estimate_par.py
grmpy/estimate/estimate_semipar.py
grmpy/plot/__init__.py
grmpy/plot/plot.py
grmpy/plot/plot_auxiliary.py
grmpy/read/__init__.py
grmpy/read/read.py
grmpy/read/read_auxiliary.py
grmpy/simulate/__init__.py
grmpy/simulate/simulate.py
grmpy/simulate/simulate_auxiliary.py
grmpy/test/__init__.py
grmpy/test/auxiliary.py
grmpy/test/conftest.py
grmpy/test/random_init.py
grmpy/test/test_integration.py
grmpy/test/test_integration_semipar.py
grmpy/test/test_quality.py
grmpy/test/test_semipar.py
grmpy/test/test_unit.py
grmpy/test/test_unit_semipar.py
grmpy/test/resources/__init__.py
grmpy/test/resources/aer-replication-mock.pkl
grmpy/test/resources/data.grmpy.dta
grmpy/test/resources/data.grmpy.pkl
grmpy/test/resources/data.grmpy.txt
grmpy/test/resources/old_regression_vault.grmpy.json
grmpy/test/resources/replication-results-mte.pkl
grmpy/test/resources/replication-results-mte_u.pkl
grmpy/test/resources/replication_semipar.grmpy.yml
grmpy-0.1.10.dist-info/LICENSE
grmpy-0.1.10.dist-info/METADATA
grmpy-0.1.10.dist-info/WHEEL
grmpy-0.1.10.dist-info/top_level.txt
grmpy-0.1.10.dist-info/RECORD
