Metadata-Version: 2.1
Name: grmpy
Version: 0.1.10
Summary: grmpy is a Python package for the simulation and estimation of the generalized Roy model.
Home-page: http://grmpy.readthedocs.io
Author: The grmpy Development Team
Author-email: eisenhauer@policy-lab.org
License: MIT
Platform: UNKNOWN
Requires-Dist: kernreg
Requires-Dist: linearmodels
Requires-Dist: numpy
Requires-Dist: matplotlib
Requires-Dist: oyaml
Requires-Dist: pandas
Requires-Dist: pytest
Requires-Dist: scikit-learn
Requires-Dist: scikit-misc
Requires-Dist: scipy
Requires-Dist: seaborn
Requires-Dist: statsmodels
